txtble/__init__.py
txtble/border_style.py
txtble/classes.py
txtble/errors.py
txtble/py.typed
txtble/util.py
txtble-0.12.2.dist-info/METADATA
txtble-0.12.2.dist-info/WHEEL
txtble-0.12.2.dist-info/licenses/LICENSE
txtble-0.12.2.dist-info/RECORD
