Metadata-Version: 2.3
Name: txtble
Version: 0.12.2
Summary: Yet another plain-text table typesetter
Project-URL: Source Code, https://github.com/jwodder/txtble
Project-URL: Bug Tracker, https://github.com/jwodder/txtble/issues
Author-email: John Thorvald Wodder II <txtble@varonathe.org>
License: MIT
Keywords: box-drawing,grid,table
Classifier: Intended Audience :: Developers
Classifier: License :: OSI Approved :: MIT License
Classifier: Programming Language :: Python :: 3
Classifier: Programming Language :: Python :: 3 :: Only
Classifier: Programming Language :: Python :: 3.8
Classifier: Programming Language :: Python :: 3.9
Classifier: Programming Language :: Python :: 3.10
Classifier: Programming Language :: Python :: 3.11
Classifier: Programming Language :: Python :: 3.12
Classifier: Programming Language :: Python :: 3.13
Classifier: Programming Language :: Python :: Implementation :: CPython
Classifier: Programming Language :: Python :: Implementation :: PyPy
Classifier: Topic :: Software Development :: User Interfaces
Classifier: Topic :: Text Processing
Classifier: Typing :: Typed
Requires-Python: >=3.8
Requires-Dist: attrs>=18.1
Requires-Dist: wcwidth~=0.2.9
